setup.py
django_shutter.egg-info/PKG-INFO
django_shutter.egg-info/SOURCES.txt
django_shutter.egg-info/dependency_links.txt
django_shutter.egg-info/requires.txt
django_shutter.egg-info/top_level.txt
shutter/__init__.py
shutter/admin.py
shutter/apps.py
shutter/flickr.py
shutter/google.py
shutter/gps.py
shutter/models.py
shutter/tasks.py
shutter/tests.py
shutter/urls.py
shutter/utils.py
shutter/views.py
shutter/management/__init__.py
shutter/management/commands/__init__.py
shutter/management/commands/import_user_exif.py
shutter/management/commands/import_user_gpx.py
shutter/management/commands/import_user_photos.py
shutter/management/commands/sync_tags.py
shutter/migrations/0001_initial.py
shutter/migrations/__init__.py
shutter/templates/shutter/_messages.html
shutter/templates/shutter/_nav.html
shutter/templates/shutter/_pagination.html
shutter/templates/shutter/admin.html
shutter/templates/shutter/base.html
shutter/templates/shutter/gallery.html
shutter/templates/shutter/gear.html
shutter/templates/shutter/index.html
shutter/templates/shutter/map.html
shutter/templates/shutter/results.html
shutter/templates/shutter/start.html
shutter/templates/shutter/tags.html