Metadata-Version: 1.0
Name: django-shutter
Version: 0.9.1
Summary: Cloud Photo Toolkit for Django
Home-page: UNKNOWN
Author: Jaco du Plessis
Author-email: jaco@jacoduplessis.co.za
License: MIT
Platform: UNKNOWN
